{
  "uris": {
    "/hybrid/user-hw/": "/index.html",
    "/hybrid/user-hw/profile/edit/:activity_id": "/index.html",
    "/hybrid/user-hw/activity/list/:admin_id": "/index.html",
    "/hybrid/user-hw/activity/join/:activity_id": "/index.html",
    "/hybrid/user-hw/trail/list": "/index.html",
    "/hybrid/user-hw/trail/detail": "/index.html",
    "/hybrid/user-hw/list/:type/:admin_id": "/index.html",
    "/user-hw-staticapp-b1cb7a079b2ffede49fa.js": "/app-b1cb7a079b2ffede49fa.js",
    "/user-hw-staticframework-b1cb7a079b2ffede49fa.js": "/framework-b1cb7a079b2ffede49fa.js",
    "/user-hw-staticapp-b1cb7a079b2ffede49fa.css": "/app-b1cb7a079b2ffede49fa.css",
    "/user-hw-staticvendor-b1cb7a079b2ffede49fa.css": "/vendor-b1cb7a079b2ffede49fa.css"
  }
}